PTVRobot/ExtinfParse.py
PTVRobot/Search.py
PTVRobot/Types.py
PTVRobot/__init__.py
PTVRobot/__main__.py
PTVRobot/static.py
PTVRobot-1.2.2.dist-info/LICENSE
PTVRobot-1.2.2.dist-info/METADATA
PTVRobot-1.2.2.dist-info/WHEEL
PTVRobot-1.2.2.dist-info/top_level.txt
PTVRobot-1.2.2.dist-info/RECORD
