Metadata-Version: 2.1
Name: PTVRobot
Version: 1.2.2
Summary: proxytv.ru IPTV Channels Parser and Robot (Like ProxyBot)
Home-page: https://github.com/NIKDISSV-Forever/ProxyTVRobot
Author: Nikita (NIKDISSV)
Author-email: nikdissv@proton.me
License: MIT
Keywords: ProxyBot,IPTV,proxytv.ru,TV,free,open
Classifier: Development Status :: 5 - Production/Stable
Classifier: Environment :: Console
Classifier: Intended Audience :: Education
Classifier: Intended Audience :: End Users/Desktop
Classifier: Intended Audience :: Information Technology
Classifier: Intended Audience :: Other Audience
Classifier: Intended Audience :: Telecommunications Industry
Classifier: License :: OSI Approved
Classifier: License :: OSI Approved :: MIT License
Classifier: Natural Language :: English
Classifier: Natural Language :: Russian
Classifier: Operating System :: OS Independent
Classifier: Programming Language :: Python :: 3
Classifier: Programming Language :: Python :: 3 :: Only
Classifier: Programming Language :: Python :: 3.8
Classifier: Programming Language :: Python :: 3.9
Classifier: Programming Language :: Python :: 3.10
Classifier: Programming Language :: Python :: 3.11
Classifier: Programming Language :: Python :: 3.12
Classifier: Topic :: Internet
Classifier: Topic :: Internet :: WWW/HTTP
Classifier: Topic :: Internet :: WWW/HTTP :: Dynamic Content
Classifier: Topic :: Multimedia :: Video
Classifier: Topic :: Utilities
Classifier: Typing :: Typed
Requires-Python: >=3.8
License-File: LICENSE
